<?xml version="1.0" encoding="UTF-8"?>
<record_update table="sp_page">
    <sp_page action="INSERT_OR_UPDATE">
        <css>.container{
  margin: 0;
  width: 100%;
}</css>
        <id>supply_chain_map</id>
        <internal>false</internal>
        <public>false</public>
        <roles/>
        <short_description/>
        <sys_class_name>sp_page</sys_class_name>
        <sys_created_by>ros11756_admin</sys_created_by>
        <sys_created_on>2017-07-18 19:44:10</sys_created_on>
        <sys_customer_update>true</sys_customer_update>
        <sys_id>30c690a5dbcc0700362cfb0e0f96196e</sys_id>
        <sys_mod_count>1</sys_mod_count>
        <sys_name>supply_chain_map</sys_name>
        <sys_package display_value="Supply Chain Management" source="x_kfna2_supply_cha">a7767b1ddb4c0700362cfb0e0f9619ec</sys_package>
        <sys_policy/>
        <sys_replace_on_upgrade>false</sys_replace_on_upgrade>
        <sys_scope display_value="Supply Chain Management">a7767b1ddb4c0700362cfb0e0f9619ec</sys_scope>
        <sys_update_name>sp_page_30c690a5dbcc0700362cfb0e0f96196e</sys_update_name>
        <sys_updated_by>ros11756_admin</sys_updated_by>
        <sys_updated_on>2017-07-18 20:41:18</sys_updated_on>
        <title>Supply Chain Map - Test Page</title>
    </sp_page>
</record_update>
